bitbox/__init__.py
bitbox/biomechanics.py
bitbox/coordination.py
bitbox/expressions.py
bitbox/data/__init__.py
bitbox/data/expression_noise_signal_stats_3DI.csv
bitbox/face_backend/__init__.py
bitbox/face_backend/backend.py
bitbox/face_backend/backend3DI.py
bitbox/face_backend/postProcess3DI.py
bitbox/face_backend/reader3DI.py
bitbox/signal_processing/__init__.py
bitbox/signal_processing/basics.py
bitbox/signal_processing/similarity.py
bitbox/signal_processing/wavelets.py
bitbox/utilities/__init__.py
bitbox/utilities/caching.py
bitbox/utilities/file_types.py
bitbox/utilities/landmarks.py
bitbox/utilities/slurm.py
bitbox/utilities/system.py
bitbox/utilities/visualization.py
bitbox-2025.10.dev1.dist-info/METADATA
bitbox-2025.10.dev1.dist-info/WHEEL
bitbox-2025.10.dev1.dist-info/licenses/LICENSE
bitbox-2025.10.dev1.dist-info/RECORD
