Metadata-Version: 2.4
Name: bitbox
Version: 2025.10.dev1
Summary: Behavioral Imaging Toolbox
Project-URL: Homepage, https://github.com/compsygroup/bitbox
Project-URL: Documentation, https://github.com/compsygroup/bitbox/wiki
Project-URL: Issues, https://github.com/compsygroup/bitbox/issues
Author-email: ComPsy Group <tuncb@chop.edu>
Maintainer-email: ComPsy Group <tuncb@chop.edu>
License: Creative Commons Attribution-NonCommercial 4.0 International
License-File: LICENSE
Keywords: behavior,body actions,computer vision,facial expressions,psychiatry,psychology
Classifier: Development Status :: 4 - Beta
Classifier: Intended Audience :: Science/Research
Classifier: License :: Free for non-commercial use
Classifier: Operating System :: OS Independent
Classifier: Programming Language :: Python :: 3
Classifier: Topic :: Scientific/Engineering
Requires-Python: >=3.8
Requires-Dist: cvxpy
Requires-Dist: kaleido
Requires-Dist: matplotlib
Requires-Dist: numpy
Requires-Dist: opencv-python
Requires-Dist: pandas
Requires-Dist: paramiko
Requires-Dist: pillow
Requires-Dist: plotly
Requires-Dist: python-dateutil
Requires-Dist: pywavelets
Requires-Dist: requests
Requires-Dist: scikit-learn
Requires-Dist: scipy
